dz_phone_number/__init__.py
dz_phone_number/dz_phones.py
dz_phone_number/enums.py
dz_phone_number/exceptions.py
tests/__init__.py
tests/conftest.py
tests/test_correctness.py
tests/test_equality.py
tests/test_immutability.py
tests/test_is.py
tests/test_is_hashable.py
tests/test_is_value_error.py
dz_phone_numbers-1.0.0.dist-info/LICENSE
dz_phone_numbers-1.0.0.dist-info/METADATA
dz_phone_numbers-1.0.0.dist-info/WHEEL
dz_phone_numbers-1.0.0.dist-info/top_level.txt
dz_phone_numbers-1.0.0.dist-info/RECORD
